moduls/__init__.py
moduls/courses.py
moduls/utils.py
albertdomprojecte1-0.5.0.dist-info/METADATA
albertdomprojecte1-0.5.0.dist-info/WHEEL
albertdomprojecte1-0.5.0.dist-info/top_level.txt
albertdomprojecte1-0.5.0.dist-info/RECORD
