Metadata-Version: 2.1
Name: albertdomprojecte1
Version: 0.5.0
Summary: Biblioteca per a consultar cursos
Home-page: https://hack4u.io
Author: Albert Domènech
